MANIFEST.in
README.rst
setup.py
collective/.DS_Store
collective/__init__.py
collective/__init__.pyc
collective.ptg.shufflegallery.egg-info/PKG-INFO
collective.ptg.shufflegallery.egg-info/SOURCES.txt
collective.ptg.shufflegallery.egg-info/dependency_links.txt
collective.ptg.shufflegallery.egg-info/entry_points.txt
collective.ptg.shufflegallery.egg-info/namespace_packages.txt
collective.ptg.shufflegallery.egg-info/not-zip-safe
collective.ptg.shufflegallery.egg-info/requires.txt
collective.ptg.shufflegallery.egg-info/top_level.txt
collective/ptg/.DS_Store
collective/ptg/__init__.py
collective/ptg/__init__.pyc
collective/ptg/shufflegallery/.DS_Store
collective/ptg/shufflegallery/__init__.py
collective/ptg/shufflegallery/__init__.pyc
collective/ptg/shufflegallery/configure.zcml
collective/ptg/shufflegallery/i18n.sh
collective/ptg/shufflegallery/shufflegallery.pt
collective/ptg/shufflegallery/resources/.DS_Store
collective/ptg/shufflegallery/resources/black-wood-ipad-wallpaper.jpg
collective/ptg/shufflegallery/resources/bluepad.jpg
collective/ptg/shufflegallery/resources/cursor_hand.png
collective/ptg/shufflegallery/resources/hand-tool.png
collective/ptg/shufflegallery/resources/hand.ico
collective/ptg/shufflegallery/resources/jquery.promptu-menu.js
collective/ptg/shufflegallery/resources/leatheriPad.jpg
collective/ptg/shufflegallery/resources/pagelink.png
collective/ptg/shufflegallery/resources/style.css
collective/ptg/shufflegallery/resources/yellowpad.png
docs/HISTORY.txt
docs/INSTALL.txt
docs/LICENSE.GPL
docs/LICENSE.txt