Metadata-Version: 1.0
Name: collective.ptg.shufflegallery
Version: 0.2
Summary: Adds shufflegallery to collective.plonetruegallery
Home-page: https://github.com/collective/collective.ptg.shufflegallery
Author: Espen Moe-Nilssen
Author-email: espen@medialog.no
License: GPL
Keywords: plone plonetruegallery addon iphone shuffle
Platform: UNKNOWN
Classifier: Framework :: Plone
Classifier: Programming Language :: Python
